code/__init__.py
najiibagecalculator-0.1.dist-info/LICENSE.txt
najiibagecalculator-0.1.dist-info/METADATA
najiibagecalculator-0.1.dist-info/WHEEL
najiibagecalculator-0.1.dist-info/top_level.txt
najiibagecalculator-0.1.dist-info/RECORD
