Metadata-Version: 2.1
Name: najiibagecalculator
Version: 0.1
Summary: This is my first package i created wich is contain basic code that calculates the age of person so i will hope you will enjoy it.
Author: Najiib Rashiid Abdi
Author-email: Cabdinajiibrcabdirashiid@gmail.com
License: UNKNOWN
Platform: UNKNOWN
Classifier: Programming Language :: Python :: 3
Classifier: License :: OSI Approved :: MIT License
Classifier: Operating System :: OS Independent
License-File: LICENSE.txt
